caches/minimum_inverse.sv
module minimum_inverse
//this module outputs the position of the lowest value 1 in the input array
#(
    LOG_INPUTS = 1
)
(
    input wire [LOG_INPUTS-1:0] in,
    output wire [2**LOG_INPUTS-1:0] out
);
    wire unsigned [$size(out)-1:0] i;
    always_comb begin
        out = 2**in;
    end
endmodule

minimum.sv
module minimum
//this module outputs the position of the lowest value 1 in the input array
//tested correctly!
#(
    LOG_INPUTS = 1
)
(
    input wire [2**LOG_INPUTS-1:0] in,
    output wire [LOG_INPUTS-1:0] out
);
    wire [$size(out)-1:0] i;
    
    always_comb begin
        i = 0;
        out = 0;
        do begin
            out = in[i] ? i : out;
            i = i+1; 
        end while (i != 0);
    end
endmodule

top.sv
`include "Sysbus.defs"

module top
#(
  ID_WIDTH = 13,
  ADDR_WIDTH = 64,
  DATA_WIDTH = 64,
  STRB_WIDTH = DATA_WIDTH/8
)
(
  input  clk,
         reset,
         hz32768timer,

  // 64-bit addresses of the program entry point and initial stack pointer
  input  [63:0] entry,
  input  [63:0] stackptr,
  input  [63:0] satp,

  // interface to connect to the bus
  output  wire [ID_WIDTH-1:0]    m_axi_awid,
  output  wire [ADDR_WIDTH-1:0]  m_axi_awaddr,
  output  wire [7:0]             m_axi_awlen,
  output  wire [2:0]             m_axi_awsize,
  output  wire [1:0]             m_axi_awburst,
  output  wire                   m_axi_awlock,
  output  wire [3:0]             m_axi_awcache,
  output  wire [2:0]             m_axi_awprot,
  output  wire                   m_axi_awvalid,
  input   wire                   m_axi_awready,
  output  wire [DATA_WIDTH-1:0]  m_axi_wdata,
  output  wire [STRB_WIDTH-1:0]  m_axi_wstrb,
  output  wire                   m_axi_wlast,
  output  wire                   m_axi_wvalid,
  input   wire                   m_axi_wready,
  input   wire [ID_WIDTH-1:0]    m_axi_bid,
  input   wire [1:0]             m_axi_bresp,
  input   wire                   m_axi_bvalid,
  output  wire                   m_axi_bready,
  output  wire [ID_WIDTH-1:0]    m_axi_arid,
  output  wire [ADDR_WIDTH-1:0]  m_axi_araddr,
  output  wire [7:0]             m_axi_arlen,
  output  wire [2:0]             m_axi_arsize,
  output  wire [1:0]             m_axi_arburst,
  output  wire                   m_axi_arlock,
  output  wire [3:0]             m_axi_arcache,
  output  wire [2:0]             m_axi_arprot,
  output  wire                   m_axi_arvalid,
  input   wire                   m_axi_arready,
  input   wire [ID_WIDTH-1:0]    m_axi_rid,
  input   wire [DATA_WIDTH-1:0]  m_axi_rdata,
  input   wire [1:0]             m_axi_rresp,
  input   wire                   m_axi_rlast,
  input   wire                   m_axi_rvalid,
  output  wire                   m_axi_rready,
  input   wire                   m_axi_acvalid,
  output  wire                   m_axi_acready,
  input   wire [ADDR_WIDTH-1:0]  m_axi_acaddr,
  input   wire [3:0]             m_axi_acsnoop
);

  logic [63:0] pc;
  reg [7:0] test_in;
  wire [2:0] test_out;
  logic test_start;
  minimum #(3) min (test_in,test_out);

  wire [2:0] test2_in;
  reg [7:0] test2_out;
  minimum_inverse #(3) min_inv (test2_in,test2_out);

  always_ff @ (posedge clk)
    if (reset) begin
      pc <= entry;
      test_in <= 0;
      test_start <= 0;
      test2_in <= 0;
    end else begin
      //$display("min: in is %b, out is %d", test_in, test_out);
      $display("min_inv: in is %b, out is %b", test2_in, test2_out);
      if (!test_start) begin
        if (test_in == 255) test_start <= 1;
        test_in <= test_in + 1;
        test2_in <= test2_in + 1;
      end else begin
        $display("Hello World!  @ %x", pc);
        $finish;
      end
    end

  initial begin
    $display("Initializing top, entry point = 0x%x", entry);
  end
endmodule

trace.vcd
$version Generated by VerilatedVcd $end
$date Mon Nov 18 15:24:15 2024
 $end
$timescale   1ps $end

 $scope module TOP $end
  $var wire  1 + clk $end
  $var wire 64 . entry [63:0] $end
  $var wire  1 - hz32768timer $end
  $var wire 64 ] m_axi_acaddr [63:0] $end
  $var wire  1 \ m_axi_acready $end
  $var wire  4 _ m_axi_acsnoop [3:0] $end
  $var wire  1 [ m_axi_acvalid $end
  $var wire 64 J m_axi_araddr [63:0] $end
  $var wire  2 N m_axi_arburst [1:0] $end
  $var wire  4 P m_axi_arcache [3:0] $end
  $var wire 13 I m_axi_arid [12:0] $end
  $var wire  8 L m_axi_arlen [7:0] $end
  $var wire  1 O m_axi_arlock $end
  $var wire  3 Q m_axi_arprot [2:0] $end
  $var wire  1 S m_axi_arready $end
  $var wire  3 M m_axi_arsize [2:0] $end
  $var wire  1 R m_axi_arvalid $end
  $var wire 64 5 m_axi_awaddr [63:0] $end
  $var wire  2 9 m_axi_awburst [1:0] $end
  $var wire  4 ; m_axi_awcache [3:0] $end
  $var wire 13 4 m_axi_awid [12:0] $end
  $var wire  8 7 m_axi_awlen [7:0] $end
  $var wire  1 : m_axi_awlock $end
  $var wire  3 < m_axi_awprot [2:0] $end
  $var wire  1 > m_axi_awready $end
  $var wire  3 8 m_axi_awsize [2:0] $end
  $var wire  1 = m_axi_awvalid $end
  $var wire 13 E m_axi_bid [12:0] $end
  $var wire  1 H m_axi_bready $end
  $var wire  2 F m_axi_bresp [1:0] $end
  $var wire  1 G m_axi_bvalid $end
  $var wire 64 U m_axi_rdata [63:0] $end
  $var wire 13 T m_axi_rid [12:0] $end
  $var wire  1 X m_axi_rlast $end
  $var wire  1 Z m_axi_rready $end
  $var wire  2 W m_axi_rresp [1:0] $end
  $var wire  1 Y m_axi_rvalid $end
  $var wire 64 ? m_axi_wdata [63:0] $end
  $var wire  1 B m_axi_wlast $end
  $var wire  1 D m_axi_wready $end
  $var wire  8 A m_axi_wstrb [7:0] $end
  $var wire  1 C m_axi_wvalid $end
  $var wire  1 , reset $end
  $var wire 64 2 satp [63:0] $end
  $var wire 64 0 stackptr [63:0] $end
  $scope module top $end
   $var wire 32 a ADDR_WIDTH [31:0] $end
   $var wire 32 a DATA_WIDTH [31:0] $end
   $var wire 32 ` ID_WIDTH [31:0] $end
   $var wire 32 b STRB_WIDTH [31:0] $end
   $var wire  1 + clk $end
   $var wire 64 . entry [63:0] $end
   $var wire  1 - hz32768timer $end
   $var wire 64 ] m_axi_acaddr [63:0] $end
   $var wire  1 \ m_axi_acready $end
   $var wire  4 _ m_axi_acsnoop [3:0] $end
   $var wire  1 [ m_axi_acvalid $end
   $var wire 64 J m_axi_araddr [63:0] $end
   $var wire  2 N m_axi_arburst [1:0] $end
   $var wire  4 P m_axi_arcache [3:0] $end
   $var wire 13 I m_axi_arid [12:0] $end
   $var wire  8 L m_axi_arlen [7:0] $end
   $var wire  1 O m_axi_arlock $end
   $var wire  3 Q m_axi_arprot [2:0] $end
   $var wire  1 S m_axi_arready $end
   $var wire  3 M m_axi_arsize [2:0] $end
   $var wire  1 R m_axi_arvalid $end
   $var wire 64 5 m_axi_awaddr [63:0] $end
   $var wire  2 9 m_axi_awburst [1:0] $end
   $var wire  4 ; m_axi_awcache [3:0] $end
   $var wire 13 4 m_axi_awid [12:0] $end
   $var wire  8 7 m_axi_awlen [7:0] $end
   $var wire  1 : m_axi_awlock $end
   $var wire  3 < m_axi_awprot [2:0] $end
   $var wire  1 > m_axi_awready $end
   $var wire  3 8 m_axi_awsize [2:0] $end
   $var wire  1 = m_axi_awvalid $end
   $var wire 13 E m_axi_bid [12:0] $end
   $var wire  1 H m_axi_bready $end
   $var wire  2 F m_axi_bresp [1:0] $end
   $var wire  1 G m_axi_bvalid $end
   $var wire 64 U m_axi_rdata [63:0] $end
   $var wire 13 T m_axi_rid [12:0] $end
   $var wire  1 X m_axi_rlast $end
   $var wire  1 Z m_axi_rready $end
   $var wire  2 W m_axi_rresp [1:0] $end
   $var wire  1 Y m_axi_rvalid $end
   $var wire 64 ? m_axi_wdata [63:0] $end
   $var wire  1 B m_axi_wlast $end
   $var wire  1 D m_axi_wready $end
   $var wire  8 A m_axi_wstrb [7:0] $end
   $var wire  1 C m_axi_wvalid $end
   $var wire 64 & pc [63:0] $end
   $var wire  1 , reset $end
   $var wire 64 2 satp [63:0] $end
   $var wire 64 0 stackptr [63:0] $end
   $var wire  3 * test2_in [2:0] $end
   $var wire  8 $ test2_out [7:0] $end
   $var wire  8 ( test_in [7:0] $end
   $var wire  3 # test_out [2:0] $end
   $var wire  1 ) test_start $end
   $scope module min $end
    $var wire 32 c LOG_INPUTS [31:0] $end
    $var wire  3 % i [2:0] $end
    $var wire  8 ( in [7:0] $end
    $var wire  3 # out [2:0] $end
   $upscope $end
   $scope module min_inv $end
    $var wire 32 c LOG_INPUTS [31:0] $end
    $var wire  8 d i [7:0] $end
    $var wire  3 * in [2:0] $end
    $var wire  8 $ out [7:0] $end
   $upscope $end
  $upscope $end
 $upscope $end
$enddefinitions $end


#0
b000 #
b00000001 $
b000 %
b0000000000000000000000000000000000000000000000000000000000000000 &
b00000000 (
0)
b000 *
1+
1,
0-
b0000000000000000000000000000000000000000000000000000000000000000 .
b0000000000000000000000000000000000111111110000000000000000000000 0
b0000000000000000000000000000000000110100010101100111000000000000 2
b0000000000000 4
b0000000000000000000000000000000000000000000000000000000000000000 5
b00000000 7
b000 8
b00 9
0:
b0000 ;
b000 <
0=
0>
b0000000000000000000000000000000000000000000000000000000000000000 ?
b00000000 A
0B
0C
0D
b0000000000000 E
b00 F
0G
0H
b0000000000000 I
b0000000000000000000000000000000000000000000000000000000000000000 J
b00000000 L
b000 M
b00 N
0O
b0000 P
b000 Q
0R
0S
b0000000000000 T
b0000000000000000000000000000000000000000000000000000000000000000 U
b00 W
0X
0Y
0Z
0[
0\
b0000000000000000000000000000000000000000000000000000000000000000 ]
b0000 _
b00000000000000000000000000001101 `
b00000000000000000000000001000000 a
b00000000000000000000000000001000 b
b00000000000000000000000000000011 c
b00000000 d
#0
1>
1D
1S
#250
0+
#250
#500
1+
#500
#750
0+
#750
#1000
1+
#1000
#1250
0+
0,
#1250
#1500
b00000010 $
b00000001 (
b001 *
1+
#1500
1-
#1750
0+
#1750
#2000
b001 #
b00000100 $
b00000010 (
b010 *
1+
#2000
#2250
0+
#2250
#2500
b00001000 $
b00000011 (
b011 *
1+
#2500
#2750
0+
#2750
#3000
b010 #
b00010000 $
b00000100 (
b100 *
1+
#3000
#3250
0+
#3250
#3500
b00100000 $
b00000101 (
b101 *
1+
#3500
#3750
0+
#3750
#4000
b01000000 $
b00000110 (
b110 *
1+
#4000
#4250
0+
#4250
#4500
b10000000 $
b00000111 (
b111 *
1+
#4500
#4750
0+
#4750
#5000
b011 #
b00000001 $
b00001000 (
b000 *
1+
#5000
#5250
0+
#5250
#5500
b00000010 $
b00001001 (
b001 *
1+
#5500
#5750
0+
#5750
#6000
b00000100 $
b00001010 (
b010 *
1+
#6000
#6250
0+
#6250
#6500
b00001000 $
b00001011 (
b011 *
1+
#6500
#6750
0+
#6750
#7000
b00010000 $
b00001100 (
b100 *
1+
#7000
#7250
0+
#7250
#7500
b00100000 $
b00001101 (
b101 *
1+
#7500
#7750
0+
#7750
#8000
b01000000 $
b00001110 (
b110 *
1+
#8000
#8250
0+
#8250
#8500
b10000000 $
b00001111 (
b111 *
1+
#8500
#8750
0+
#8750
#9000
b100 #
b00000001 $
b00010000 (
b000 *
1+
#9000
#9250
0+
#9250
#9500
b00000010 $
b00010001 (
b001 *
1+
#9500
#9750
0+
#9750
#10000
b00000100 $
b00010010 (
b010 *
1+
#10000
#10250
0+
#10250
#10500
b00001000 $
b00010011 (
b011 *
1+
#10500
#10750
0+
#10750
#11000
b00010000 $
b00010100 (
b100 *
1+
#11000
#11250
0+
#11250
#11500
b00100000 $
b00010101 (
b101 *
1+
#11500
#11750
0+
#11750
#12000
b01000000 $
b00010110 (
b110 *
1+
#12000
#12250
0+
#12250
#12500
b10000000 $
b00010111 (
b111 *
1+
#12500
#12750
0+
#12750
#13000
b00000001 $
b00011000 (
b000 *
1+
#13000
#13250
0+
#13250
#13500
b00000010 $
b00011001 (
b001 *
1+
#13500
#13750
0+
#13750
#14000
b00000100 $
b00011010 (
b010 *
1+
#14000
#14250
0+
#14250
#14500
b00001000 $
b00011011 (
b011 *
1+
#14500
#14750
0+
#14750
#15000
b00010000 $
b00011100 (
b100 *
1+
#15000
#15250
0+
#15250
#15500
b00100000 $
b00011101 (
b101 *
1+
#15500
#15750
0+
#15750
#16000
b01000000 $
b00011110 (
b110 *
1+
#16000
#16250
0+
#16250
#16500
b10000000 $
b00011111 (
b111 *
1+
#16500
#16750
0+
#16750
#17000
b101 #
b00000001 $
b00100000 (
b000 *
1+
#17000
#17250
0+
#17250
#17500
b00000010 $
b00100001 (
b001 *
1+
#17500
#17750
0+
#17750
#18000
b00000100 $
b00100010 (
b010 *
1+
#18000
#18250
0+
#18250
#18500
b00001000 $
b00100011 (
b011 *
1+
#18500
#18750
0+
#18750
#19000
b00010000 $
b00100100 (
b100 *
1+
#19000
#19250
0+
#19250
#19500
b00100000 $
b00100101 (
b101 *
1+
#19500
#19750
0+
#19750
#20000
b01000000 $
b00100110 (
b110 *
1+
#20000
#20250
0+
#20250
#20500
b10000000 $
b00100111 (
b111 *
1+
#20500
#20750
0+
#20750
#21000
b00000001 $
b00101000 (
b000 *
1+
#21000
#21250
0+
#21250
#21500
b00000010 $
b00101001 (
b001 *
1+
#21500
#21750
0+
#21750
#22000
b00000100 $
b00101010 (
b010 *
1+
#22000
#22250
0+
#22250
#22500
b00001000 $
b00101011 (
b011 *
1+
#22500
#22750
0+
#22750
#23000
b00010000 $
b00101100 (
b100 *
1+
#23000
#23250
0+
#23250
#23500
b00100000 $
b00101101 (
b101 *
1+
#23500
#23750
0+
#23750
#24000
b01000000 $
b00101110 (
b110 *
1+
#24000
#24250
0+
#24250
#24500
b10000000 $
b00101111 (
b111 *
1+
#24500
#24750
0+
#24750
#25000
b00000001 $
b00110000 (
b000 *
1+
#25000
#25250
0+
#25250
#25500
b00000010 $
b00110001 (
b001 *
1+
#25500
#25750
0+
#25750
#26000
b00000100 $
b00110010 (
b010 *
1+
#26000
#26250
0+
#26250
#26500
b00001000 $
b00110011 (
b011 *
1+
#26500
#26750
0+
#26750
#27000
b00010000 $
b00110100 (
b100 *
1+
#27000
#27250
0+
#27250
#27500
b00100000 $
b00110101 (
b101 *
1+
#27500
#27750
0+
#27750
#28000
b01000000 $
b00110110 (
b110 *
1+
#28000
#28250
0+
#28250
#28500
b10000000 $
b00110111 (
b111 *
1+
#28500
#28750
0+
#28750
#29000
b00000001 $
b00111000 (
b000 *
1+
#29000
#29250
0+
#29250
#29500
b00000010 $
b00111001 (
b001 *
1+
#29500
#29750
0+
#29750
#30000
b00000100 $
b00111010 (
b010 *
1+
#30000
#30250
0+
#30250
#30500
b00001000 $
b00111011 (
b011 *
1+
#30500
#30750
0+
#30750
#31000
b00010000 $
b00111100 (
b100 *
1+
#31000
#31250
0+
#31250
#31500
b00100000 $
b00111101 (
b101 *
1+
#31500
#31750
0+
#31750
#32000
b01000000 $
b00111110 (
b110 *
1+
#32000
#32250
0+
#32250
#32500
b10000000 $
b00111111 (
b111 *
1+
#32500
#32750
0+
#32750
#33000
b110 #
b00000001 $
b01000000 (
b000 *
1+
#33000
#33250
0+
#33250
#33500
b00000010 $
b01000001 (
b001 *
1+
#33500
#33750
0+
#33750
#34000
b00000100 $
b01000010 (
b010 *
1+
#34000
#34250
0+
#34250
#34500
b00001000 $
b01000011 (
b011 *
1+
#34500
#34750
0+
#34750
#35000
b00010000 $
b01000100 (
b100 *
1+
#35000
#35250
0+
#35250
#35500
b00100000 $
b01000101 (
b101 *
1+
#35500
#35750
0+
#35750
#36000
b01000000 $
b01000110 (
b110 *
1+
#36000
#36250
0+
#36250
#36500
b10000000 $
b01000111 (
b111 *
1+
#36500
#36750
0+
#36750
#37000
b00000001 $
b01001000 (
b000 *
1+
#37000
#37250
0+
#37250
#37500
b00000010 $
b01001001 (
b001 *
1+
#37500
#37750
0+
#37750
#38000
b00000100 $
b01001010 (
b010 *
1+
#38000
#38250
0+
#38250
#38500
b00001000 $
b01001011 (
b011 *
1+
#38500
#38750
0+
#38750
#39000
b00010000 $
b01001100 (
b100 *
1+
#39000
#39250
0+
#39250
#39500
b00100000 $
b01001101 (
b101 *
1+
#39500
#39750
0+
#39750
#40000
b01000000 $
b01001110 (
b110 *
1+
#40000
#40250
0+
#40250
#40500
b10000000 $
b01001111 (
b111 *
1+
#40500
#40750
0+
#40750
#41000
b00000001 $
b01010000 (
b000 *
1+
#41000
#41250
0+
#41250
#41500
b00000010 $
b01010001 (
b001 *
1+
#41500
#41750
0+
#41750
#42000
b00000100 $
b01010010 (
b010 *
1+
#42000
#42250
0+
#42250
#42500
b00001000 $
b01010011 (
b011 *
1+
#42500
#42750
0+
#42750
#43000
b00010000 $
b01010100 (
b100 *
1+
#43000
#43250
0+
#43250
#43500
b00100000 $
b01010101 (
b101 *
1+
#43500
#43750
0+
#43750
#44000
b01000000 $
b01010110 (
b110 *
1+
#44000
#44250
0+
#44250
#44500
b10000000 $
b01010111 (
b111 *
1+
#44500
#44750
0+
#44750
#45000
b00000001 $
b01011000 (
b000 *
1+
#45000
#45250
0+
#45250
#45500
b00000010 $
b01011001 (
b001 *
1+
#45500
#45750
0+
#45750
#46000
b00000100 $
b01011010 (
b010 *
1+
#46000
#46250
0+
#46250
#46500
b00001000 $
b01011011 (
b011 *
1+
#46500
#46750
0+
#46750
#47000
b00010000 $
b01011100 (
b100 *
1+
#47000
#47250
0+
#47250
#47500
b00100000 $
b01011101 (
b101 *
1+
#47500
#47750
0+
#47750
#48000
b01000000 $
b01011110 (
b110 *
1+
#48000
#48250
0+
#48250
#48500
b10000000 $
b01011111 (
b111 *
1+
#48500
#48750
0+
#48750
#49000
b00000001 $
b01100000 (
b000 *
1+
#49000
#49250
0+
#49250
#49500
b00000010 $
b01100001 (
b001 *
1+
#49500
#49750
0+
#49750
#50000
b00000100 $
b01100010 (
b010 *
1+
#50000
#50250
0+
#50250
#50500
b00001000 $
b01100011 (
b011 *
1+
#50500
#50750
0+
#50750
#51000
b00010000 $
b01100100 (
b100 *
1+
#51000
#51250
0+
#51250
#51500
b00100000 $
b01100101 (
b101 *
1+
#51500
#51750
0+
#51750
#52000
b01000000 $
b01100110 (
b110 *
1+
#52000
#52250
0+
#52250
#52500
b10000000 $
b01100111 (
b111 *
1+
#52500
#52750
0+
#52750
#53000
b00000001 $
b01101000 (
b000 *
1+
#53000
#53250
0+
#53250
#53500
b00000010 $
b01101001 (
b001 *
1+
#53500
#53750
0+
#53750
#54000
b00000100 $
b01101010 (
b010 *
1+
#54000
#54250
0+
#54250
#54500
b00001000 $
b01101011 (
b011 *
1+
#54500
#54750
0+
#54750
#55000
b00010000 $
b01101100 (
b100 *
1+
#55000
#55250
0+
#55250
#55500
b00100000 $
b01101101 (
b101 *
1+
#55500
#55750
0+
#55750
#56000
b01000000 $
b01101110 (
b110 *
1+
#56000
#56250
0+
#56250
#56500
b10000000 $
b01101111 (
b111 *
1+
#56500
#56750
0+
#56750
#57000
b00000001 $
b01110000 (
b000 *
1+
#57000
#57250
0+
#57250
#57500
b00000010 $
b01110001 (
b001 *
1+
#57500
#57750
0+
#57750
#58000
b00000100 $
b01110010 (
b010 *
1+
#58000
#58250
0+
#58250
#58500
b00001000 $
b01110011 (
b011 *
1+
#58500
#58750
0+
#58750
#59000
b00010000 $
b01110100 (
b100 *
1+
#59000
#59250
0+
#59250
#59500
b00100000 $
b01110101 (
b101 *
1+
#59500
#59750
0+
#59750
#60000
b01000000 $
b01110110 (
b110 *
1+
#60000
#60250
0+
#60250
#60500
b10000000 $
b01110111 (
b111 *
1+
#60500
#60750
0+
#60750
#61000
b00000001 $
b01111000 (
b000 *
1+
#61000
#61250
0+
#61250
#61500
b00000010 $
b01111001 (
b001 *
1+
#61500
#61750
0+
#61750
#62000
b00000100 $
b01111010 (
b010 *
1+
#62000
#62250
0+
#62250
#62500
b00001000 $
b01111011 (
b011 *
1+
#62500
#62750
0+
#62750
#63000
b00010000 $
b01111100 (
b100 *
1+
#63000
#63250
0+
#63250
#63500
b00100000 $
b01111101 (
b101 *
1+
#63500
#63750
0+
#63750
#64000
b01000000 $
b01111110 (
b110 *
1+
#64000
#64250
0+
#64250
#64500
b10000000 $
b01111111 (
b111 *
1+
#64500
#64750
0+
#64750
#65000
b111 #
b00000001 $
b10000000 (
b000 *
1+
#65000
#65250
0+
#65250
#65500
b00000010 $
b10000001 (
b001 *
1+
#65500
#65750
0+
#65750
#66000
b00000100 $
b10000010 (
b010 *
1+
#66000
#66250
0+
#66250
#66500
b00001000 $
b10000011 (
b011 *
1+
#66500
#66750
0+
#66750
#67000
b00010000 $
b10000100 (
b100 *
1+
#67000
#67250
0+
#67250
#67500
b00100000 $
b10000101 (
b101 *
1+
#67500
#67750
0+
#67750
#68000
b01000000 $
b10000110 (
b110 *
1+
#68000
#68250
0+
#68250
#68500
b10000000 $
b10000111 (
b111 *
1+
#68500
#68750
0+
#68750
#69000
b00000001 $
b10001000 (
b000 *
1+
#69000
#69250
0+
#69250
#69500
b00000010 $
b10001001 (
b001 *
1+
#69500
#69750
0+
#69750
#70000
b00000100 $
b10001010 (
b010 *
1+
#70000
#70250
0+
#70250
#70500
b00001000 $
b10001011 (
b011 *
1+
#70500
#70750
0+
#70750
#71000
b00010000 $
b10001100 (
b100 *
1+
#71000
#71250
0+
#71250
#71500
b00100000 $
b10001101 (
b101 *
1+
#71500
#71750
0+
#71750
#72000
b01000000 $
b10001110 (
b110 *
1+
#72000
#72250
0+
#72250
#72500
b10000000 $
b10001111 (
b111 *
1+
#72500
#72750
0+
#72750
#73000
b00000001 $
b10010000 (
b000 *
1+
#73000
#73250
0+
#73250
#73500
b00000010 $
b10010001 (
b001 *
1+
#73500
#73750
0+
#73750
#74000
b00000100 $
b10010010 (
b010 *
1+
#74000
#74250
0+
#74250
#74500
b00001000 $
b10010011 (
b011 *
1+
#74500
#74750
0+
#74750
#75000
b00010000 $
b10010100 (
b100 *
1+
#75000
#75250
0+
#75250
#75500
b00100000 $
b10010101 (
b101 *
1+
#75500
#75750
0+
#75750
#76000
b01000000 $
b10010110 (
b110 *
1+
#76000
#76250
0+
#76250
#76500
b10000000 $
b10010111 (
b111 *
1+
#76500
#76750
0+
#76750
#77000
b00000001 $
b10011000 (
b000 *
1+
#77000
#77250
0+
#77250
#77500
b00000010 $
b10011001 (
b001 *
1+
#77500
#77750
0+
#77750
#78000
b00000100 $
b10011010 (
b010 *
1+
#78000
#78250
0+
#78250
#78500
b00001000 $
b10011011 (
b011 *
1+
#78500
#78750
0+
#78750
#79000
b00010000 $
b10011100 (
b100 *
1+
#79000
#79250
0+
#79250
#79500
b00100000 $
b10011101 (
b101 *
1+
#79500
#79750
0+
#79750
#80000
b01000000 $
b10011110 (
b110 *
1+
#80000
#80250
0+
#80250
#80500
b10000000 $
b10011111 (
b111 *
1+
#80500
#80750
0+
#80750
#81000
b00000001 $
b10100000 (
b000 *
1+
#81000
#81250
0+
#81250
#81500
b00000010 $
b10100001 (
b001 *
1+
#81500
#81750
0+
#81750
#82000
b00000100 $
b10100010 (
b010 *
1+
#82000
#82250
0+
#82250
#82500
b00001000 $
b10100011 (
b011 *
1+
#82500
#82750
0+
#82750
#83000
b00010000 $
b10100100 (
b100 *
1+
#83000
#83250
0+
#83250
#83500
b00100000 $
b10100101 (
b101 *
1+
#83500
#83750
0+
#83750
#84000
b01000000 $
b10100110 (
b110 *
1+
#84000
#84250
0+
#84250
#84500
b10000000 $
b10100111 (
b111 *
1+
#84500
#84750
0+
#84750
#85000
b00000001 $
b10101000 (
b000 *
1+
#85000
#85250
0+
#85250
#85500
b00000010 $
b10101001 (
b001 *
1+
#85500
#85750
0+
#85750
#86000
b00000100 $
b10101010 (
b010 *
1+
#86000
#86250
0+
#86250
#86500
b00001000 $
b10101011 (
b011 *
1+
#86500
#86750
0+
#86750
#87000
b00010000 $
b10101100 (
b100 *
1+
#87000
#87250
0+
#87250
#87500
b00100000 $
b10101101 (
b101 *
1+
#87500
#87750
0+
#87750
#88000
b01000000 $
b10101110 (
b110 *
1+
#88000
#88250
0+
#88250
#88500
b10000000 $
b10101111 (
b111 *
1+
#88500
#88750
0+
#88750
#89000
b00000001 $
b10110000 (
b000 *
1+
#89000
#89250
0+
#89250
#89500
b00000010 $
b10110001 (
b001 *
1+
#89500
#89750
0+
#89750
#90000
b00000100 $
b10110010 (
b010 *
1+
#90000
#90250
0+
#90250
#90500
b00001000 $
b10110011 (
b011 *
1+
#90500
#90750
0+
#90750
#91000
b00010000 $
b10110100 (
b100 *
1+
#91000
#91250
0+
#91250
#91500
b00100000 $
b10110101 (
b101 *
1+
#91500
#91750
0+
#91750
#92000
b01000000 $
b10110110 (
b110 *
1+
#92000
#92250
0+
#92250
#92500
b10000000 $
b10110111 (
b111 *
1+
#92500
#92750
0+
#92750
#93000
b00000001 $
b10111000 (
b000 *
1+
#93000
#93250
0+
#93250
#93500
b00000010 $
b10111001 (
b001 *
1+
#93500
#93750
0+
#93750
#94000
b00000100 $
b10111010 (
b010 *
1+
#94000
#94250
0+
#94250
#94500
b00001000 $
b10111011 (
b011 *
1+
#94500
#94750
0+
#94750
#95000
b00010000 $
b10111100 (
b100 *
1+
#95000
#95250
0+
#95250
#95500
b00100000 $
b10111101 (
b101 *
1+
#95500
#95750
0+
#95750
#96000
b01000000 $
b10111110 (
b110 *
1+
#96000
#96250
0+
#96250
#96500
b10000000 $
b10111111 (
b111 *
1+
#96500
#96750
0+
#96750
#97000
b00000001 $
b11000000 (
b000 *
1+
#97000
#97250
0+
#97250
#97500
b00000010 $
b11000001 (
b001 *
1+
#97500
#97750
0+
#97750
#98000
b00000100 $
b11000010 (
b010 *
1+
#98000
#98250
0+
#98250
#98500
b00001000 $
b11000011 (
b011 *
1+
#98500
#98750
0+
#98750
#99000
b00010000 $
b11000100 (
b100 *
1+
#99000
#99250
0+
#99250
#99500
b00100000 $
b11000101 (
b101 *
1+
#99500
#99750
0+
#99750
#100000
b01000000 $
b11000110 (
b110 *
1+
#100000
#100250
0+
#100250
#100500
b10000000 $
b11000111 (
b111 *
1+
#100500
#100750
0+
#100750
#101000
b00000001 $
b11001000 (
b000 *
1+
#101000
#101250
0+
#101250
#101500
b00000010 $
b11001001 (
b001 *
1+
#101500
#101750
0+
#101750
#102000
b00000100 $
b11001010 (
b010 *
1+
#102000
#102250
0+
#102250
#102500
b00001000 $
b11001011 (
b011 *
1+
#102500
#102750
0+
#102750
#103000
b00010000 $
b11001100 (
b100 *
1+
#103000
#103250
0+
#103250
#103500
b00100000 $
b11001101 (
b101 *
1+
#103500
#103750
0+
#103750
#104000
b01000000 $
b11001110 (
b110 *
1+
#104000
#104250
0+
#104250
#104500
b10000000 $
b11001111 (
b111 *
1+
#104500
#104750
0+
#104750
#105000
b00000001 $
b11010000 (
b000 *
1+
#105000
#105250
0+
#105250
#105500
b00000010 $
b11010001 (
b001 *
1+
#105500
#105750
0+
#105750
#106000
b00000100 $
b11010010 (
b010 *
1+
#106000
#106250
0+
#106250
#106500
b00001000 $
b11010011 (
b011 *
1+
#106500
#106750
0+
#106750
#107000
b00010000 $
b11010100 (
b100 *
1+
#107000
#107250
0+
#107250
#107500
b00100000 $
b11010101 (
b101 *
1+
#107500
#107750
0+
#107750
#108000
b01000000 $
b11010110 (
b110 *
1+
#108000
#108250
0+
#108250
#108500
b10000000 $
b11010111 (
b111 *
1+
#108500
#108750
0+
#108750
#109000
b00000001 $
b11011000 (
b000 *
1+
#109000
#109250
0+
#109250
#109500
b00000010 $
b11011001 (
b001 *
1+
#109500
#109750
0+
#109750
#110000
b00000100 $
b11011010 (
b010 *
1+
#110000
#110250
0+
#110250
#110500
b00001000 $
b11011011 (
b011 *
1+
#110500
#110750
0+
#110750
#111000
b00010000 $
b11011100 (
b100 *
1+
#111000
#111250
0+
#111250
#111500
b00100000 $
b11011101 (
b101 *
1+
#111500
#111750
0+
#111750
#112000
b01000000 $
b11011110 (
b110 *
1+
#112000
#112250
0+
#112250
#112500
b10000000 $
b11011111 (
b111 *
1+
#112500
#112750
0+
#112750
#113000
b00000001 $
b11100000 (
b000 *
1+
#113000
#113250
0+
#113250
#113500
b00000010 $
b11100001 (
b001 *
1+
#113500
#113750
0+
#113750
#114000
b00000100 $
b11100010 (
b010 *
1+
#114000
#114250
0+
#114250
#114500
b00001000 $
b11100011 (
b011 *
1+
#114500
#114750
0+
#114750
#115000
b00010000 $
b11100100 (
b100 *
1+
#115000
#115250
0+
#115250
#115500
b00100000 $
b11100101 (
b101 *
1+
#115500
#115750
0+
#115750
#116000
b01000000 $
b11100110 (
b110 *
1+
#116000
#116250
0+
#116250
#116500
b10000000 $
b11100111 (
b111 *
1+
#116500
#116750
0+
#116750
#117000
b00000001 $
b11101000 (
b000 *
1+
#117000
#117250
0+
#117250
#117500
b00000010 $
b11101001 (
b001 *
1+
#117500
#117750
0+
#117750
#118000
b00000100 $
b11101010 (
b010 *
1+
#118000
#118250
0+
#118250
#118500
b00001000 $
b11101011 (
b011 *
1+
#118500
#118750
0+
#118750
#119000
b00010000 $
b11101100 (
b100 *
1+
#119000
#119250
0+
#119250
#119500
b00100000 $
b11101101 (
b101 *
1+
#119500
#119750
0+
#119750
#120000
b01000000 $
b11101110 (
b110 *
1+
#120000
#120250
0+
#120250
#120500
b10000000 $
b11101111 (
b111 *
1+
#120500
#120750
0+
#120750
#121000
b00000001 $
b11110000 (
b000 *
1+
#121000
#121250
0+
#121250
#121500
b00000010 $
b11110001 (
b001 *
1+
#121500
#121750
0+
#121750
#122000
b00000100 $
b11110010 (
b010 *
1+
#122000
#122250
0+
#122250
#122500
b00001000 $
b11110011 (
b011 *
1+
#122500
#122750
0+
#122750
#123000
b00010000 $
b11110100 (
b100 *
1+
#123000
#123250
0+
#123250
#123500
b00100000 $
b11110101 (
b101 *
1+
#123500
